pychassiscli-0.4.2.dist-info/METADATA
pychassiscli-0.4.2.dist-info/WHEEL
pychassiscli-0.4.2.dist-info/entry_points.txt
pychassiscli/__init__.py
pychassiscli/cli.py
pychassiscli/templates/apiflask/.apiflaskenv
pychassiscli/templates/apiflask/.dockerignore
pychassiscli/templates/apiflask/.drone.yml
pychassiscli/templates/apiflask/.gitignore
pychassiscli/templates/apiflask/Dockerfile
pychassiscli/templates/apiflask/README.md
pychassiscli/templates/apiflask/app/APIDesc.md
pychassiscli/templates/apiflask/app/__init__.py
pychassiscli/templates/apiflask/app/api/__init__.py
pychassiscli/templates/apiflask/app/api/v1/__init__.py
pychassiscli/templates/apiflask/app/api/v1/api.py
pychassiscli/templates/apiflask/app/api/v1/exception/__init__.py
pychassiscli/templates/apiflask/app/api/v1/exception/api.py
pychassiscli/templates/apiflask/app/api/v1/schema/__init__.py
pychassiscli/templates/apiflask/app/api/v1/schema/api.py
pychassiscli/templates/apiflask/app/config/__init__.py
pychassiscli/templates/apiflask/app/config/config.py
pychassiscli/templates/apiflask/app/util/__init__.py
pychassiscli/templates/apiflask/app/util/auth.py
pychassiscli/templates/apiflask/app/util/common.py
pychassiscli/templates/apiflask/app/util/exception.py
pychassiscli/templates/apiflask/docker-compose-build.yml
pychassiscli/templates/apiflask/docker-compose-run.yml
pychassiscli/templates/apiflask/docker-deploy.sh
pychassiscli/templates/apiflask/gunicorn.conf.py
pychassiscli/templates/apiflask/requirements.txt
pychassiscli/templates/apiflask/starter.py
pychassiscli/templates/metric-configs/grafana.json.mako
pychassiscli/templates/metric-configs/grafana_conf/config/grafana.ini
pychassiscli/templates/metric-configs/grafana_conf/provisioning/dashboards/all.yaml
pychassiscli/templates/metric-configs/grafana_conf/provisioning/datasources/all.yaml
pychassiscli/templates/metric-configs/prometheus_conf/prometheus.yml
pychassiscli/templates/metric-configs/statsd_config.js
pychassiscli/templates/metric-configs/statsd_mapping.yml.mako
pychassiscli/templates/nameko/.dockerignore
pychassiscli/templates/nameko/.gitignore
pychassiscli-0.4.2.dist-info/RECORD
