Metadata-Version: 2.1
Name: pychassiscli
Version: 0.4.2
Summary: A lightweight Python distributed microservice command line tool
Author-Email: BryantHe <bryantsisu@qq.com>
License: MIT
Classifier: Development Status :: 3 - Alpha
Classifier: Environment :: Web Environment
Classifier: Intended Audience :: Developers
Classifier: License :: OSI Approved :: MIT License
Classifier: Programming Language :: Python :: 3
Classifier: Topic :: Software Development :: Libraries :: Python Modules
Project-URL: Homepage, https://github.com/Bryanthelol/pychassiscli
Project-URL: Source code, https://github.com/Bryanthelol/pychassiscli
Project-URL: Bug tracker, https://github.com/Bryanthelol/pychassiscli/issues
Requires-Python: >=3.8
Requires-Dist: python-on-whales>=0.68.0
Requires-Dist: rich>=13.7.0
Requires-Dist: click>=8.1.7
Requires-Dist: mako>=1.3.2
Requires-Dist: pytest>=8.0.0
